#######################################################################################################################################
<poster>HackerMil</poster>
<fanart>http://farm6.staticflickr.com/5460/10217454264_7eda59c6f3_o.png</fanart>
#######################################################################################################################################

<popup>
<name>[COLOR red]CLICK HERE[/COLOR] [COLOR aqua]FOR INFO ON JOINING THE VIP CLUB AND DETAILS[/COLOR]</name>
<popImage>http://farm3.staticflickr.com/2851/10218170123_bb90f51c7e_o.png</popImage>
<thumbnail>http://farm6.staticflickr.com/5510/10217412394_e1da1b6fcc_o.jpg</thumbnail>
</popup>


#########################################################################


<item>
<title>[COLOR blue]Fight[/COLOR] Bradley vs Marquez Oct. 12, 2013 HD</title>
<link>
<sublink>http://BillionUploads.com/er0a0kfsmsw4</sublink>
<sublink>http://hugefiles.net/52eefzb4u74e</sublink>
<sublink>http://www.putlocker.com/file/D323932B94F2EDFC</sublink>
<sublink>http://mightyupload.com/py8fchqfxaos</sublink>
<sublink>http://180upload.com/tjcper4b3wyv</sublink>
<sublink>http://epicshare.net/1bxwcog2pzu2</sublink>
<sublink>http://lemuploads.com/1bxwcog2pzu2</sublink>
</link>
<thumbnail>http://upload.wikimedia.org/wikipedia/en/a/af/BradleyVsMarquez.png</thumbnail>
</item>

<item>
<title>[COLOR blue]Fight[/COLOR] UFC Fight Night 29 Maia vs Shields [COLOR lime]10/10[/COLOR]</title>
<link>
<sublink>http://180upload.com/hals9qi2jvlo</sublink>
<sublink>http://movreel.com/h4xci4vhs6kg</sublink>
<sublink>http://hugefiles.net/bj58jzjxf4u3</sublink>  
</link>
<thumbnail>http://upload.wikimedia.org/wikipedia/en/thumb/8/8b/Improved_UFN_29_poster.ppg.jpg/461px-Improved_UFN_29_poster.ppg.jpg</thumbnail>
</item>

<item>
<title>[COLOR blue]Fight[/COLOR] Miguel Cotto vs Delvin Rodriguez Oct. 5, 2013 [COLOR lime]10/7[/COLOR]</title>
<link>
<sublink>http://BillionUploads.com/l64qsiwlid89</sublink>
<sublink>http://hugefiles.net/7lnxs3wi78yf</sublink>
<sublink>http://www.putlocker.com/file/68D2954AAF4F4782</sublink>
<sublink>http://mightyupload.com/u4pqgmn88v6d</sublink>
<sublink>http://180upload.com/i18410eyugi9</sublink>
<sublink>http://epicshare.net/jkfgwtwpv3na</sublink>
<sublink>http://lemuploads.com/jkfgwtwpv3na</sublink>
</link>
<thumbnail>http://fightpreviews.net/wp-content/uploads/2013/09/1004842_612666728764822_816301804_n_zpsf0c342c6.jpg</thumbnail>
</item>

<item>
<title>[COLOR blue]Fight[/COLOR] Wladimir Klitschko vs Alexander Povetkin Oct. 5, 2013 [COLOR lime]10/7[/COLOR]</title>
<link>
<sublink>http://BillionUploads.com/cbbheom47fjr</sublink>
<sublink>http://hugefiles.net/1wifwsmd8s11</sublink>
<sublink>http://www.putlocker.com/file/1EA34E84A9D4FCAE</sublink>
<sublink>http://mightyupload.com/ap8f9c0jia6u</sublink>
<sublink>http://180upload.com/v085nqym3ko1</sublink>
<sublink>http://epicshare.net/ron1num4i701</sublink>
<sublink>http://lemuploads.com/moah8274877y</sublink>
</link>
<thumbnail>http://www.klitschko.com/uploads/tx_templavoila/WK_vs_Povetkin_web_gross_02.jpg</thumbnail>
</item>

<item>
<title>[COLOR blue]Event[/COLOR] Bellator 102 Oct. 4, 2013 [COLOR lime]10/5[/COLOR]</title>
<link>
<sublink>http://billionuploads.com/6gquwqbipj55</sublink>
<sublink>http://www.putlocker.com/file/C2BF551D131AE4AF</sublink>
<sublink>http://180upload.com/w9peq2qo46gj</sublink>
<sublink></sublink>
<sublink></sublink>
<sublink></sublink>
<sublink></sublink>
<sublink></sublink>
</link>
<thumbnail>http://3.bp.blogspot.com/-BaF6fM_pp5E/Ukmnyzup7_I/AAAAAAAAOaI/OYJK03whtrc/s1600/Bellator+102.jpg</thumbnail>
</item>

